CHANGES.rst
DESCRIPTION.rst
LICENSE
MANIFEST.in
README.md
setup.py
src/wai.annotations.layersegments.egg-info/PKG-INFO
src/wai.annotations.layersegments.egg-info/SOURCES.txt
src/wai.annotations.layersegments.egg-info/dependency_links.txt
src/wai.annotations.layersegments.egg-info/entry_points.txt
src/wai.annotations.layersegments.egg-info/namespace_packages.txt
src/wai.annotations.layersegments.egg-info/requires.txt
src/wai.annotations.layersegments.egg-info/top_level.txt
src/wai/annotations/layer_segments/__init__.py
src/wai/annotations/layer_segments/component/_FromLayerSegments.py
src/wai/annotations/layer_segments/component/_LayerSegmentsWriter.py
src/wai/annotations/layer_segments/component/_ToLayerSegments.py
src/wai/annotations/layer_segments/component/__init__.py
src/wai/annotations/layer_segments/specifier/_LayerSegmentsSinkStateSpecifier.py
src/wai/annotations/layer_segments/specifier/_LayerSegmentsSourceStageSpecifier.py
src/wai/annotations/layer_segments/specifier/__init__.py
src/wai/annotations/layer_segments/util/_LabelSeparatorMixin.py
src/wai/annotations/layer_segments/util/__init__.py
src/wai/annotations/layer_segments/util/_format.py